{
	"capacity_threshold" : "10",
	"global_title" : "LTT 10 TB+ Storage Rankings",
	"post_open" : "[post=",
	"post_mid" : "]",
	"post_close" : "[/post]",
	"capacity_unit" : " TB",
	"after_rank_padding" : "2",
	"after_username_padding" : "1",
	"after_enclosure_padding" : "2",
	"before_enclosure_padding" : "3",
	"before_notes_padding" : "2",
	"after_os_stor_padding" : "0",
	"before_capacity_padding" : "0",
	"bold_open" : "[b]",
	"bold_close" : "[/b]",
	"total_capacity_note" : "Total Storage Capacity: ",
	"font_large_open" : "[size=6]",
	"font_size_close" : "[/size]",
	"font_medium_open" : "[size=5]",
	"horiz_separator" : "[hr]",
	"newline" : "\n",
	"priority_note" : "Sorting priority: First by capacity descending, then by post date, ascending.",
	"last_updated_note" : "Last updated: ",
	"stats_title" : "Statistics",
	"stats_system_summary_title" : "Systems Summary",
	"capacity_range" : "10",
	"capacity_groups" : {
		"10 TB ≤ capacity < 20 TB" : "20",
		"20 TB ≤ capacity < 30 TB" : "30",
		"30 TB ≤ capacity < 40 TB" : "40",
		"40 TB ≤ capacity < 50 TB" : "50",
		"50 TB ≤ capacity < 60 TB" : "60",
		"60 TB ≤ capacity < 70 TB" : "70",
		"70 TB ≤ capacity < 80 TB" : "80",
		"80 TB ≤ capacity < 90 TB" : "90"
	},
	"capacity_groups_contrib" : {
		"10 TB ≤ capacity < 20 TB" : "20",
		"20 TB ≤ capacity < 30 TB" : "30",
		"30 TB ≤ capacity < 40 TB" : "40",
		"40 TB ≤ capacity < 50 TB" : "50",
		"50 TB ≤ capacity < 60 TB" : "60",
		"60 TB ≤ capacity < 70 TB" : "70",
		"70 TB ≤ capacity < 80 TB" : "80",
		"80 TB ≤ capacity < 90 TB" : "90"
	},
	"grouped_caps_title" : "Grouped Distribution",
	"mean_sys_capacity_title" : "Arithmetic Mean Capacity",
	"median_sys_capacity_title" : "Median Capacity",
	"mode_sys_capacity_title" : "Mode (most common capacity)",
	"no_of_occurrences" : "number of occurrences: ",
	"no_of_uniq_caps" : "Number of Unique Capacities",
	"sys_summary_extra_padding" : "8",
	"capacity_groups_padding" : "16",
	"hdd_summary_extra_padding" : "8",
	"hdd_summary_title" : "HDD Statistics",
	"total_drives" : "Total Number of Drives",
	"avg_dr_per_system" : "Average Drives per System",
	"total_comb_cap" : "Total Combined Capacity",
	"avg_dr_cap" : "Average Drive Capacity",
	"med_dr_cap" : "Median Drive Capacity",
	"hdd_table_col_spacing_size" : "4",
	"hdd_table_col_spacing_vendor" : "4",
	"vendor_list" : [
		"HGST",
		"Seagate",
		"WD",
		"unspecified",
		"Toshiba"
	],
	"hdd_by_size_title" : "HDD Statistics, by Size",
	"hdd_by_vendor_title" : "HDD Statistics, by Vendor",
	"by_size_size_col_title" : "Capacity",
	"by_size_count_col_title" : "              Count",
	"by_size_sum_col_title" : "              Sum",
	"by_size_perc_col_title" : "       Percentage of Total",
	"by_size_perc_count_col_title" : "                                                    Count",
	"by_size_perc_cap_col_title" : "     Capacity",
	"by_vendor_vendor_col_title" : "Vendor",
	"by_vendor_count_col_title" : "                Count",
	"by_vendor_sum_col_title" : "              Sum",
	"by_vendor_perc_col_title" : "       Percentage of Total",
	"by_vendor_perc_count_col_title" : "                                                    Count",
	"by_vendor_perc_cap_col_title" : "     Capacity",
	"total_table_footer_vendor" : "TOTAL          ",
	"total_table_footer_size" : "TOTAL",
	"total_table_footer_vendor_padding_col1" : "5",
	"total_table_footer_vendor_padding_col2" : "14",
	"total_table_footer_size_padding_col1" : "5",
	"total_table_footer_size_padding_col2" : "14",
	"abbreviations_key_title" : "Abbreviations Key",
	"abbreviations_key" : [
		"[b]WS[/b]         Windows Server",
		"[b]WHS[/b]        Windows Home Server",
		"[b]SHR[/b]        Synology Hybrid RAID",
		"[b]StSp[/b]       Storage Spaces",
		"[b]RD[/b]         RAID (unspecified if hardware or software)",
		"[b]HwRD[/b]       Hardware RAID",
		"[b]SwRD[/b]       Software RAID",
		"[b]FlRD[/b]       FlexRAID"
	],
	"unranked_list_title_1" : "Noteworthy Builds w/ <10 TB storage,",
	"unranked_list_title_2" : " unranked, unsorted",
	"pie_chart_percentage_threshold" : "0.05",
	"pie_chart_hdd_count_by_size_title" : "HDD Count Distribution by Size",
	"pie_chart_hdd_cap_by_size_title" : "HDD Combined Capacity Distribution by Size",
	"pie_chart_hdd_count_by_vendor_title" : "HDD Count Distribution by Vendor",
	"pie_chart_hdd_cap_by_vendor_title" : "HDD Combined Capacity Distribution by Vendor",
	"pie_chart_total_hdd_count_label" : "Total HDD Count: ",
	"pie_chart_total_hdd_cap_label" : "Total Capacity: ",
	"pie_chart_configs" : {
		"logo_resize" : "0.2",
		"logo_position" : "LR",
		"t_margin" : "30",
		"b_margin" : "50",
		"l_margin" : "20",
		"r_margin" : "20",
		"3d" : "1",
		"transparent" : "0",
		"dclrs" : [
			"pink", 
			"purple",
			"cyan",
			"marine",
			"lpurple",
			"lgray",
			"lorange",
			"lgreen",
			"lbrown",
			"lyellow",
			"lred"
		],
		"labelclr" : "black",
		"textclr" : "black",
		"axislabelclr" : "black"
	},
	"hbar_graph_configs" : {
		"y_label" : "System Capacity (TB)",
		"x_label" : "Username/System",
		"title" : "Ranking List",
		"y_tick_number" : "8",
		"transparent" : "0",
		"logo_resize" : "0.1",
		"logo_position" : "LR",
		"t_margin" : "30",
		"b_margin" : "50",
		"l_margin" : "20",
		"r_margin" : "20",
		"show_values" : "1",
		"bar_spacing" : "6",
		"dclrs" : [ "lblue" ]
	},
	"hbar_hdd_count_by_size_configs" : {
		"y_label" : "Group Count",
		"x_label" : "Capacity Group",
		"title" : "System Groupings by Count",
		"y_tick_number" : "5",
		"transparent" : "0",
		"logo_resize" : "0.1",
		"logo_position" : "LR",
		"t_margin" : "30",
		"b_margin" : "50",
		"l_margin" : "20",
		"r_margin" : "20",
		"show_values" : "1",
		"bar_spacing" : "6",
        "text_space" : "18",
        "values_space" : "8",
		"dclrs" : [ "lblue" ]
	},
	"hbar_hdd_cap_by_size_configs" : {
		"y_label" : "Group Count",
		"x_label" : "Capacity Group",
		"title" : "System Groupings by Count",
		"y_tick_number" : "5",
		"transparent" : "0",
		"logo_resize" : "0.1",
		"logo_position" : "LR",
		"t_margin" : "30",
		"b_margin" : "50",
		"l_margin" : "20",
		"r_margin" : "20",
		"show_values" : "1",
		"bar_spacing" : "6",
        "text_space" : "18",
        "values_space" : "8",
		"dclrs" : [ "lblue" ]
	},
	"grouped_hbar_by_count_configs" : {
		"y_label" : "Group Count",
		"x_label" : "Capacity Group",
		"title" : "System Groupings by Count",
		"y_tick_number" : "5",
		"transparent" : "0",
		"logo_resize" : "0.1",
		"logo_position" : "LR",
		"t_margin" : "30",
		"b_margin" : "50",
		"l_margin" : "20",
		"r_margin" : "20",
		"show_values" : "1",
		"bar_spacing" : "6",
        "text_space" : "18",
        "values_space" : "8",
		"dclrs" : [ "lblue" ]
	},
	"grouped_hbar_by_contrib_configs" : {
		"y_label" : "Group Combined Capacity (TB)",
		"x_label" : "Capacity Group",
		"title" : "System Groupings by Contribution",
		"y_tick_number" : "5",
		"transparent" : "0",
		"logo_resize" : "0.1",
		"logo_position" : "LR",
		"t_margin" : "30",
		"b_margin" : "50",
		"l_margin" : "20",
		"r_margin" : "20",
		"show_values" : "1",
		"bar_spacing" : "6",
        "text_space" : "18",
        "values_space" : "8",
		"dclrs" : [ "lblue" ]
	},
	"img_dir" : "images",
	"logo_img" : "logo.png",
	"hdd_cap_by_vendor_img" : "hdd_cap_by_vendor.png",
	"hdd_count_by_vendor_img" : "hdd_count_by_vendor.png",
	"hdd_cap_by_size_img" : "hdd_cap_by_size.png",
	"hdd_count_by_size_img" : "hdd_count_by_size.png",
	"pie_chart_title_size" : "32",
	"pie_chart_value_size" : "24",
	"pie_chart_label_size" : "28",
	"ranking_list_plot_title" : "Ranking List, Graphical Version",
	"ranking_chart_img" : "ltt_storage_rankings.png",
	"ranking_chart_title_size" : "22",
	"ranking_chart_label_size" : "14",
	"ranking_chart_axis_size" : "12",
	"grouped_plot_title_size" : "18",
	"grouped_plot_label_size" : "14",
	"grouped_plot_axis_size" : "12",
	"grouped_plot_y_axis_size" : "8",
    "grouped_plot_by_count_img" : "ltt_plot_grouped_by_count.png",
    "grouped_plot_by_contrib_img" : "ltt_plot_grouped_by_contrib.png",
    "grouped_plot_by_count_title" : "System Groupings, by Count",
    "grouped_plot_by_contrib_title" : "System Groupings, Contributions to Total Capacity",
    "grouped_plot_by_count_label" : "Total System Count: ",
    "grouped_plot_by_contrib_label" : "Total Capacity: ",
    "hbar_max_y_scaling_factor" : "1.2",
	"img_server" : "http://www.alpenwasser.net/images/w600/"
}
